fuo_netease/__init__.py
fuo_netease/api.py
fuo_netease/consts.py
fuo_netease/downloader.py
fuo_netease/excs.py
fuo_netease/login_controller.py
fuo_netease/models.py
fuo_netease/page_fav.py
fuo_netease/provider.py
fuo_netease/provider_ui.py
fuo_netease/schemas.py
fuo_netease/ui.py
fuo_netease/assets/icon.svg
fuo_netease/cloud_helpers/__init__.py
fuo_netease/cloud_helpers/cloud_api.py
fuo_netease/cloud_helpers/security.py
fuo_netease-1.0.4.dist-info/METADATA
fuo_netease-1.0.4.dist-info/WHEEL
fuo_netease-1.0.4.dist-info/entry_points.txt
fuo_netease-1.0.4.dist-info/top_level.txt
fuo_netease-1.0.4.dist-info/RECORD
