Metadata-Version: 2.1
Name: fuo_netease
Version: 1.0.4
Summary: feeluown netease plugin
Home-page: https://github.com/feeluown/feeluown-netease
Author: Cosven
Author-email: yinshaowen241@gmail.com
Keywords: feeluown,plugin,netease
Classifier: Development Status :: 3 - Alpha
Classifier: Programming Language :: Python :: 3.8
Classifier: Programming Language :: Python :: 3.9
Classifier: Programming Language :: Python :: 3.10
Classifier: Programming Language :: Python :: 3 :: Only
Requires-Dist: feeluown (>=4.0a0)
Requires-Dist: beautifulsoup4
Requires-Dist: pycryptodome
Requires-Dist: marshmallow (>=3.0)
Requires-Dist: requests
Requires-Dist: mutagen (>=1.37)
Provides-Extra: dev
Requires-Dist: flake8 ; extra == 'dev'
Requires-Dist: pytest (>=5.4.0) ; extra == 'dev'
Requires-Dist: pytest-cov ; extra == 'dev'
